{
    "version": "https://jsonfeed.org/version/1",
    "title": "Jason&#x27;s Computing Guides",
    "description": "",
    "home_page_url": "https://aindien.com",
    "feed_url": "https://aindien.com/feed.json",
    "user_comment": "",
    "author": {
        "name": "Jason Moore"
    },
    "items": [
        {
            "id": "https://aindien.com/encapsulating-data-in-python.html",
            "url": "https://aindien.com/encapsulating-data-in-python.html",
            "title": "Encapsulating Data in Python",
            "summary": "<div>These are my notes on encapsulating data in python.</div>\n<div>",
            "image": "https://aindien.com/media/posts/185/trianglify-lowres9.png",
            "author": {
                "name": "Jason Moore"
            },
            "tags": [
                   "Python"
            ],
            "date_published": "2024-10-05T17:41:30-05:00",
            "date_modified": "2024-10-05T17:42:44-05:00"
        },
        {
            "id": "https://aindien.com/processes-in-linux.html",
            "url": "https://aindien.com/processes-in-linux.html",
            "title": "Processes in Linux",
            "summary": "<p>These are my notes on processes in linux.</p>\n",
            "image": "https://aindien.com/media/posts/184/trianglify-lowres9.png",
            "author": {
                "name": "Jason Moore"
            },
            "tags": [
                   "Linux"
            ],
            "date_published": "2024-10-03T19:22:51-05:00",
            "date_modified": "2024-10-03T19:24:04-05:00"
        },
        {
            "id": "https://aindien.com/accessing-files-in-python.html",
            "url": "https://aindien.com/accessing-files-in-python.html",
            "title": "Accessing Files in Python",
            "summary": "<p>These are my notes on accessing files in python.</p>\n",
            "image": "https://aindien.com/media/posts/183/trianglify-lowres9.png",
            "author": {
                "name": "Jason Moore"
            },
            "tags": [
                   "Python"
            ],
            "date_published": "2024-09-30T23:27:44-05:00",
            "date_modified": "2024-09-30T23:28:25-05:00"
        },
        {
            "id": "https://aindien.com/permissions-in-linux.html",
            "url": "https://aindien.com/permissions-in-linux.html",
            "title": "Permissions in Linux",
            "summary": "<div>These are my notes and thoughts on permissions in linux.</div>\n<div>",
            "image": "https://aindien.com/media/posts/182/trianglify-lowres9.png",
            "author": {
                "name": "Jason Moore"
            },
            "tags": [
                   "Linux"
            ],
            "date_published": "2024-09-28T20:53:31-05:00",
            "date_modified": "2024-09-28T20:55:01-05:00"
        },
        {
            "id": "https://aindien.com/modifying-strings-in-python.html",
            "url": "https://aindien.com/modifying-strings-in-python.html",
            "title": "Modifying Strings in Python",
            "summary": "<p>These are my notes on modifying strings in python.</p>\n",
            "image": "https://aindien.com/media/posts/181/trianglify-lowres9.png",
            "author": {
                "name": "Jason Moore"
            },
            "tags": [
                   "Python"
            ],
            "date_published": "2024-09-27T17:34:31-05:00",
            "date_modified": "2024-09-27T20:55:04-05:00"
        },
        {
            "id": "https://aindien.com/input-and-output-redirection-in-linux.html",
            "url": "https://aindien.com/input-and-output-redirection-in-linux.html",
            "title": "Input and Output Redirection in Linux",
            "summary": "<p>These are my notes on input and output redirection in Linux.</p>\n",
            "image": "https://aindien.com/media/posts/180/trianglify-lowres8.png",
            "author": {
                "name": "Jason Moore"
            },
            "tags": [
                   "Linux"
            ],
            "date_published": "2024-09-17T14:27:57-05:00",
            "date_modified": "2024-09-24T00:02:13-05:00"
        },
        {
            "id": "https://aindien.com/using-strings-in-python.html",
            "url": "https://aindien.com/using-strings-in-python.html",
            "title": "Using Strings in Python",
            "summary": "<p>These are my notes on using strings in python. </p>\n",
            "image": "https://aindien.com/media/posts/179/trianglify-lowres8.png",
            "author": {
                "name": "Jason Moore"
            },
            "tags": [
                   "Python"
            ],
            "date_published": "2024-09-15T15:18:35-05:00",
            "date_modified": "2024-09-24T00:02:22-05:00"
        },
        {
            "id": "https://aindien.com/using-modules-in-python.html",
            "url": "https://aindien.com/using-modules-in-python.html",
            "title": "Using Modules in Python",
            "summary": "<p>This is my guide on using modules in python.</p>\n",
            "image": "https://aindien.com/media/posts/178/trianglify-lowres8.png",
            "author": {
                "name": "Jason Moore"
            },
            "tags": [
                   "Python"
            ],
            "date_published": "2024-09-12T16:40:30-05:00",
            "date_modified": "2024-09-24T00:02:31-05:00"
        },
        {
            "id": "https://aindien.com/aliases-in-git.html",
            "url": "https://aindien.com/aliases-in-git.html",
            "title": "Aliases in Git",
            "summary": "<p>These are my notes on aliases in git.</p>\n",
            "image": "https://aindien.com/media/posts/177/trianglify-lowres6.png",
            "author": {
                "name": "Jason Moore"
            },
            "tags": [
                   "Git"
            ],
            "date_published": "2024-08-25T13:34:03-05:00",
            "date_modified": "2024-09-24T00:02:41-05:00"
        },
        {
            "id": "https://aindien.com/sharing-your-home-network.html",
            "url": "https://aindien.com/sharing-your-home-network.html",
            "title": "Sharing Your Home Network",
            "summary": "<p>These are my notes and worked examples on sharing your home network.</p>\n",
            "image": "https://aindien.com/media/posts/176/trianglify-lowres6.png",
            "author": {
                "name": "Jason Moore"
            },
            "tags": [
                   "Networking"
            ],
            "date_published": "2024-08-22T20:16:29-05:00",
            "date_modified": "2024-09-24T00:02:52-05:00"
        }
    ]
}
